atek/__init__.py
atek/configs/__init__.py
atek/data_download/__init__.py
atek/data_download/atek_data_store_download.py
atek/data_loaders/__init__.py
atek/data_loaders/atek_raw_dataloader_as_cubercnn.py
atek/data_loaders/atek_wds_dataloader.py
atek/data_loaders/cubercnn_model_adaptor.py
atek/data_loaders/depth_anything2_model_adaptor.py
atek/data_loaders/sam2_model_adaptor.py
atek/data_loaders/test/__init__.py
atek/data_loaders/test/atek_wds_dataloader_test.py
atek/data_preprocess/__init__.py
atek/data_preprocess/atek_data_sample.py
atek/data_preprocess/atek_wds_writer.py
atek/data_preprocess/genera_atek_preprocessor_factory.py
atek/data_preprocess/general_atek_preprocessor.py
atek/data_preprocess/processors/__init__.py
atek/data_preprocess/processors/aria_camera_processor.py
atek/data_preprocess/processors/depth_image_processor.py
atek/data_preprocess/processors/efm_gt_processor.py
atek/data_preprocess/processors/mps_online_calib_processor.py
atek/data_preprocess/processors/mps_semidense_processor.py
atek/data_preprocess/processors/mps_traj_processor.py
atek/data_preprocess/processors/obb2_gt_processor.py
atek/data_preprocess/processors/obb3_gt_processor.py
atek/data_preprocess/sample_builders/__init__.py
atek/data_preprocess/sample_builders/atek_data_paths_provider.py
atek/data_preprocess/sample_builders/efm_sample_builder.py
atek/data_preprocess/sample_builders/obb_sample_builder.py
atek/data_preprocess/subsampling_lib/__init__.py
atek/data_preprocess/subsampling_lib/temporal_subsampler.py
atek/data_preprocess/test/__init__.py
atek/data_preprocess/test/aria_camera_processor_test.py
atek/data_preprocess/test/atek_data_sample_test.py
atek/data_preprocess/test/depth_image_processor_test.py
atek/data_preprocess/test/file_io_utils_test.py
atek/data_preprocess/test/mps_processor_test.py
atek/data_preprocess/test/obb2_gt_processor_test.py
atek/data_preprocess/test/obb3_gt_processor_test.py
atek/data_preprocess/test/obb_sample_builder_test.py
projectaria_atek-1.0.0.dist-info/LICENSE
projectaria_atek-1.0.0.dist-info/METADATA
projectaria_atek-1.0.0.dist-info/WHEEL
projectaria_atek-1.0.0.dist-info/top_level.txt
projectaria_atek-1.0.0.dist-info/RECORD
